LICENSE
picked_group_fdr/__init__.py
picked_group_fdr/__main__.py
picked_group_fdr/columns/__init__.py
picked_group_fdr/columns/base.py
picked_group_fdr/columns/diann_protein_annotations.py
picked_group_fdr/columns/evidence_ids.py
picked_group_fdr/columns/fastlfq.py
picked_group_fdr/columns/fragpipe_protein_annotations.py
picked_group_fdr/columns/id_type.py
picked_group_fdr/columns/indistinguishable_proteins.py
picked_group_fdr/columns/lfq.py
picked_group_fdr/columns/modifications.py
picked_group_fdr/columns/peptide_count.py
picked_group_fdr/columns/protein_annotations.py
picked_group_fdr/columns/protein_probability.py
picked_group_fdr/columns/sequence_coverage.py
picked_group_fdr/columns/spectral_count.py
picked_group_fdr/columns/sum_and_ibaq.py
picked_group_fdr/columns/tmt.py
picked_group_fdr/columns/top_peptide.py
picked_group_fdr/columns/triqler.py
picked_group_fdr/competition.py
picked_group_fdr/digest.py
picked_group_fdr/digestfast.cpp
picked_group_fdr/digestfast.html
picked_group_fdr/digestfast.pyx
picked_group_fdr/digestion_params.py
picked_group_fdr/entrapment.py
picked_group_fdr/fdr.py
picked_group_fdr/graphs.py
picked_group_fdr/grouping.py
picked_group_fdr/helpers.py
picked_group_fdr/methods/classic_no_grouping.toml
picked_group_fdr/methods/classic_no_grouping_no_remap.toml
picked_group_fdr/methods/classic_protein_group.toml
picked_group_fdr/methods/classic_rescued_subset_grouping.toml
picked_group_fdr/methods/classic_subset_grouping.toml
picked_group_fdr/methods/diann.toml
picked_group_fdr/methods/discard_picked.toml
picked_group_fdr/methods/discard_picked_mq_input.toml
picked_group_fdr/methods/fragpipe.toml
picked_group_fdr/methods/maxquant.toml
picked_group_fdr/methods/maxquant_mq_best.toml
picked_group_fdr/methods/maxquant_mq_best_picked.toml
picked_group_fdr/methods/maxquant_perc_best.toml
picked_group_fdr/methods/maxquant_perc_best_picked.toml
picked_group_fdr/methods/maxquant_picked.toml
picked_group_fdr/methods/picked_protein_group.toml
picked_group_fdr-0.9.0.dist-info/LICENSE
picked_group_fdr-0.9.0.dist-info/METADATA
picked_group_fdr-0.9.0.dist-info/WHEEL
picked_group_fdr-0.9.0.dist-info/RECORD
