Metadata-Version: 2.1
Name: picked_group_fdr
Version: 0.9.0
Summary: Scalable, accurate and sensitive protein group FDRs for large-scale mass spectrometry experiments
Home-page: https://github.com/kusterlab/picked_group_fdr
License: Apache-2.0
Keywords: mass spectrometry,protein inference,proteomics
Author: Matthew The
Author-email: matthew.the@tum.de
Requires-Python: >=3.10,<3.14
Classifier: License :: OSI Approved :: Apache Software License
Classifier: Programming Language :: Python :: 3
Classifier: Programming Language :: Python :: 3.10
Classifier: Programming Language :: Python :: 3.11
Classifier: Programming Language :: Python :: 3.12
Provides-Extra: gui
Requires-Dist: Bottleneck (>=1.3.5,<2.0.0)
Requires-Dist: cython (>=0.29.21)
Requires-Dist: job-pool (>=0.3.2)
Requires-Dist: matplotlib (>=3.3.1,<4.0.0)
Requires-Dist: mokapot (>=0.3)
Requires-Dist: networkx (>=2.4,<3.0)
Requires-Dist: numpy (>=1.18)
Requires-Dist: pyarrow (>=19.0.1,<20.0.0)
Requires-Dist: pyqt5 (>=5.15.7,<6.0.0) ; extra == "gui"
Requires-Dist: scipy (>=1.9,<2.0)
Requires-Dist: toml (>=0.10.2,<0.11.0)
Requires-Dist: triqler (>=0.7.0)
Project-URL: Repository, https://github.com/kusterlab/picked_group_fdr
